pytest_rpc/__init__.py
pytest_rpc/fixtures.py
pytest_rpc/helpers.py
pytest_rpc-1.1.1.dist-info/LICENSE
pytest_rpc-1.1.1.dist-info/METADATA
pytest_rpc-1.1.1.dist-info/WHEEL
pytest_rpc-1.1.1.dist-info/entry_points.txt
pytest_rpc-1.1.1.dist-info/top_level.txt
pytest_rpc-1.1.1.dist-info/RECORD
