Metadata-Version: 2.1
Name: pytest-rpc
Version: 1.1.1
Summary: Extend py.test for RPC OpenStack testing.
Home-page: https://github.com/rcbops/pytest-rpc
Author: rpc-automation
Author-email: rpc-automation@rackspace.com
License: Apache Software License 2.0
Keywords: py.test pytest pytest-rpc
Platform: UNKNOWN
Classifier: Development Status :: 4 - Beta
Classifier: Framework :: Pytest
Classifier: Intended Audience :: Developers
Classifier: License :: OSI Approved :: Apache Software License
Classifier: Natural Language :: English
Classifier: Operating System :: OS Independent
Classifier: Programming Language :: Python :: 2
Classifier: Programming Language :: Python :: 2.7
Classifier: Programming Language :: Python :: 3
Classifier: Programming Language :: Python :: 3.4
Classifier: Programming Language :: Python :: 3.5
Classifier: Programming Language :: Python :: 3.6
Classifier: Topic :: Software Development :: Libraries :: Python Modules
Requires-Python: >=2.7, !=3.0.*, !=3.1.*, !=3.2.*, !=3.3.*
Requires-Dist: configparser
Requires-Dist: packaging (~=18.0)
Requires-Dist: paramiko
Requires-Dist: pytest (~=3.6)
Requires-Dist: setuptools
Requires-Dist: sh
Requires-Dist: shade
